halsim_gui/__init__.py
halsim_gui/main.py
halsim_gui/py.typed
halsim_gui/version.py
halsim_gui/_ext/__init__.py
halsim_gui/_ext/main.cpp
halsim_gui/include/HALDataSource.h
halsim_gui/include/HALProvider.h
halsim_gui/include/HALSimGui.h
halsim_gui/include/HALSimGuiExt.h
halsim_gui/include/LICENSE.md
halsim_gui/include/SimDeviceGui.h
halsim_gui/include/ThirdPartyNotices.txt
halsim_gui/lib/libhalsim_gui.so
halsim_gui/_ext/_halsim_gui_ext.cpython-311-aarch64-linux-gnu.so
halsim_gui/_ext/_halsim_gui_ext.pyi
halsim_gui/_ext/_init__halsim_gui_ext.py
halsim_gui/_ext/halsim_gui_ext.pc
robotpy_halsim_gui-2025.3.2.3.dist-info/METADATA
robotpy_halsim_gui-2025.3.2.3.dist-info/WHEEL
robotpy_halsim_gui-2025.3.2.3.dist-info/entry_points.txt
robotpy_halsim_gui-2025.3.2.3.dist-info/RECORD
