Metadata-Version: 2.4
Name: robotpy-halsim-gui
Version: 2025.3.2.3
Summary: WPILib simulation GUI
Project-URL: Source code, https://github.com/robotpy/mostrobotpy
Author-email: RobotPy Development Team <robotpy@googlegroups.com>
License-Expression: BSD-3-Clause
Requires-Dist: pyntcore==2025.3.2.3
Requires-Dist: robotpy-hal==2025.3.2.3
Requires-Dist: robotpy-wpimath==2025.3.2.3
Requires-Dist: robotpy-wpiutil==2025.3.2.3
